bayes_mef/__init__.py
bayes_mef/algos.py
bayes_mef/mef_launcher.py
bayes_mef/utils.py
bayes_mef-0.1.9.dist-info/LICENSE
bayes_mef-0.1.9.dist-info/METADATA
bayes_mef-0.1.9.dist-info/WHEEL
bayes_mef-0.1.9.dist-info/RECORD
