Metadata-Version: 2.3
Name: bayes_mef
Version: 0.1.9
Summary: Python implementation of the Bayesian MEF method
License: BSD-3-Clause
Author: Shantanu Kodgirwar
Author-email: shantanu.kodgirwar@uni-jena.de
Requires-Python: >=3.9,<3.13
Classifier: License :: OSI Approved :: BSD License
Classifier: Programming Language :: Python :: 3
Classifier: Programming Language :: Python :: 3.9
Classifier: Programming Language :: Python :: 3.10
Classifier: Programming Language :: Python :: 3.11
Classifier: Programming Language :: Python :: 3.12
Requires-Dist: h5py (>=3.9,<4.0)
Requires-Dist: matplotlib (>=3.7,<4.0)
Requires-Dist: numpy (>=1.22,<3.0)
Requires-Dist: scikit-image (>=0.21,<1.0)
Requires-Dist: scipy (>=1.11,<2.0)
Requires-Dist: tqdm (>=4.66,<5.0)
Project-URL: Repository, https://github.com/microscopic-image-analysis/bayes-mef
